cdecimal.so
pypi_cdecimal-2.3.dist-info/DESCRIPTION.rst
pypi_cdecimal-2.3.dist-info/METADATA
pypi_cdecimal-2.3.dist-info/metadata.json
pypi_cdecimal-2.3.dist-info/RECORD
pypi_cdecimal-2.3.dist-info/top_level.txt
pypi_cdecimal-2.3.dist-info/WHEEL
