Metadata-Version: 2.0
Name: pypi-cdecimal
Version: 2.3
Summary: Fast arbitrary precision correctly-rounded decimal floating point arithmetic.
Home-page: http://www.bytereef.org/mpdecimal/index.html
Author: Stefan Krah
Author-email: skrah@bytereef.org
License: BSD License
Download-URL: http://www.bytereef.org/software/mpdecimal/releases/cdecimal-2.3.tar.gz
Keywords: decimal,floating point,correctly-rounded,arithmetic,arbitrary precision
Platform: Many
Classifier: Development Status :: 5 - Production/Stable
Classifier: Intended Audience :: Developers
Classifier: Intended Audience :: Education
Classifier: Intended Audience :: End Users/Desktop
Classifier: Intended Audience :: Financial and Insurance Industry
Classifier: Intended Audience :: Science/Research
Classifier: License :: OSI Approved :: BSD License
Classifier: Programming Language :: C
Classifier: Programming Language :: Python :: 2.5
Classifier: Programming Language :: Python :: 2.6
Classifier: Programming Language :: Python :: 2.7
Classifier: Programming Language :: Python :: 3
Classifier: Programming Language :: Python :: 3.1
Classifier: Programming Language :: Python :: 3.2
Classifier: Operating System :: OS Independent
Classifier: Topic :: Scientific/Engineering :: Mathematics
Classifier: Topic :: Software Development
